Workbook
Name Pay_Rate: 'Income'!$D$8
Name Est_Hours: 'Income'!$D$9
Name Est_OT: 'Income'!$D$10
Name OT_Rate: 'Income'!$D$11
Name Tax_Pct: 'Income'!$D$12
Name Pay_Date: 'Income'!$B$27:$B$50
Name Pay_Net: 'Income'!$D$27:$D$50
Name Gov_Amt: 'Income'!$C$57:$C$63
Name Gov_Start: 'Income'!$D$57:$D$63
Name Gov_Int: 'Income'!$F$57:$F$63
Name Fixed_Amt: 'Expenses'!$C$8:$C$15
Name Fixed_Start: 'Expenses'!$D$8:$D$15
Name Disc_Date: 'Expenses'!$B$21:$B$44
Name Disc_Amt: 'Expenses'!$D$21:$D$44
Name Bill_Amt: 'Bills & Subscriptions'!$C$8:$C$19
Name Bill_DueDay: 'Bills & Subscriptions'!$D$8:$D$19
Name Bill_InBudget: 'Bills & Subscriptions'!$E$8:$E$19
Name Bill_Start: 'Bills & Subscriptions'!$F$8:$F$19
Name Plan_Date: 'Bills & Subscriptions'!$C$25:$C$30
Name Plan_Amt: 'Bills & Subscriptions'!$D$25:$D$30
Name Cal_Month: 'Bills & Subscriptions'!$C$35
Name Side_Inc_Date: 'Side Income'!$B$12:$B$33
Name Side_Inc_Amt: 'Side Income'!$E$12:$E$33
Name Side_Exp_Date: 'Side Income'!$G$12:$G$33
Name Side_Exp_Amt: 'Side Income'!$J$12:$J$33
Name Saven_Bal: 'Savings & Goals'!$C$8
Name Saven_Rate: 'Savings & Goals'!$D$8
Name Membership: 'Savings & Goals'!$C$9
Name WS_TFSA: 'Savings & Goals'!$C$10
Name WS_TFSA_Auto: 'Savings & Goals'!$D$10
Name WS_HISA: 'Savings & Goals'!$C$11
Name RBC_Chq: 'Savings & Goals'!$C$12
Name Sav_Total: 'Savings & Goals'!$C$13
Name EF_Progress: 'Savings & Goals'!$F$19
Name Goal7k_Pct: 'Savings & Goals'!$F$20
Name Goal7k_Target: 'Savings & Goals'!$C$20
Name OnTrack7k: 'Savings & Goals'!$I$20
Name Trip_Pct: 'Savings & Goals'!$F$21
Name Trip_Current: 'Savings & Goals'!$D$21
Name INR_Owed: 'Debt Tracker'!$C$7
Name INR_per_CAD: 'Debt Tracker'!$C$8
Name INR_Pay: 'Debt Tracker'!$C$9
Name India_Rate: 'Debt Tracker'!$C$10
Name India_CAD: 'Debt Tracker'!$F$7
Name India_Pay: 'Debt Tracker'!$F$9
Name Avion_Bal: 'Debt Tracker'!$L$8
Name Debt_Name: 'Debt Tracker'!$B$16:$B$27
Name Debt_Amt: 'Debt Tracker'!$C$16:$C$27
Name Debt_Months: 'Debt Tracker'!$G$16:$G$27
Name Month_Labels: 'MonthData'!$B$2:$B$13
Name Month_Dates: 'MonthData'!$A$2:$A$13
Name Sel_Label: 'Dashboard'!$D$4
Name Sel_Month: 'Dashboard'!$P$4
Name Fixed_Name: 'Expenses'!$B$8:$B$15
Name NW_Goal: 'Net Worth'!$E$9
Name Habit_Month: 'Habit Tracker'!$C$4

Sheet START HERE
C2: START HERE
C3: Joel's money workbook — built so you never have to touch a formula.
B6: THE ONE RULE
B7: You only ever type into the gold cells. Everything else fills itself in. This is a gold cell → | H7: type here
B8: If a cell isn't gold, leave it alone — it's doing math for you.
B10: WHAT EACH TAB IS FOR
B11: Dashboard | D11: Your overview. Pick a month from the gold dropdown at the top — all the cards and charts update.
B12: Income | D12: Log each real paycheque (date + net $). Government money (tax refund, CGEB, OTB) is set up to add itself.
B13: Expenses | D13: Your fixed bills, plus a takeout log so you can watch extra spending against your $100 grocery budget.
B14: Bills & Subscriptions | D14: Tick a box when each bill is paid. The calendar shows which day each bill lands on.
B15: Debt Tracker | D15: India loan converts from rupees automatically. Pay the Avion card in full — it warns you if you don't.
B16: Savings & Goals | D16: Update your account balances. Set goal targets + monthly plans; progress bars do the rest.
B17: Net Worth | D17: Everything you own minus everything you owe. Pulls straight from your other tabs.
B18: Side Income | D18: Ready for when you start freelancing — log income & costs, see your profit.
B19: Habit Tracker | D19: Tick a box each day. The % and charts show how you're doing.
B21: YOUR SIMPLE ROUTINE — WHICH GOLD CELLS TO UPDATE, AND WHEN
B22: EVERY WEEK
B23: • Income tab → add any paycheque you got (date + net $).
B24: • Expenses tab → add takeout/extra spends as they happen.
B25: • Habit tab → tick your daily boxes.
B27: EVERY MONTH
B28: • Savings tab → update each account balance from your apps.
B29: • Bills tab → tick off bills as you pay them.
B30: • Debt tab → update the Avion balance (aim for $0).
B31: • Dashboard → switch the month dropdown to the new month.
B33: ONE-TIME SETUP (already done for you)
B34: • Pay rate, deduction %, fixed bill amounts.
... B37: • Just tweak these if your real numbers change.

Sheet Dashboard
C2: DASHBOARD
C3: Your whole money picture. Pick a month below — everything updates itself.
B4: VIEWING MONTH: | D4: Jun 2026 | F4: ← change this to switch the whole dashboard | P4: =INDEX(Month_Dates,MATCH(Sel_Label,Month_Labels,0))
B7: TOTAL SAVINGS | E7: THIS MONTH INCOME | H7: THIS MONTH EXPENSES | K7: LEFTOVER THIS MONTH | N7: EMERGENCY FUND | Q7: ON TRACK FOR $7K?
B8: =Sav_Total | E8: =INDEX(MonthData!$F$2:$F$13,MATCH(Sel_Label,Month_Labels,0)) | H8: =INDEX(MonthData!$J$2:$J$13,MATCH(Sel_Label,Month_Labels,0)) | K8: =INDEX(MonthData!$K$2:$K$13,MATCH(Sel_Label,Month_Labels,0)) | N8: =EF_Progress | Q8: =OnTrack7k
B11: THIS YEAR (12-MONTH WINDOW)
B13: INCOME SO FAR THIS YEAR | H13: EXPENSES SO FAR THIS YEAR | N13: SAVED SO FAR THIS YEAR
B14: =SUMPRODUCT((MonthData!C2:C13>0)*MonthData!F2:F13) | H14: =SUMPRODUCT((MonthData!C2:C13>0)*MonthData!J2:J13) | N14: =SUMPRODUCT((MonthData!C2:C13>0)*MonthData!K2:K13)
B16: INCOME VS EXPENSES BY MONTH | M16: WHERE MY MONEY GOES
B35: SAVINGS GROWING OVER TIME | M35: GOAL PROGRESS
M37: Emergency Fund → $7,150 | S37: =EF_Progress
M38: =EF_Progress
M39: $7,000 by Dec 2026 | S39: =Goal7k_Pct
M40: =Goal7k_Pct
M41: India Trip → $5,000 | S41: =Trip_Pct
M42: =Trip_Pct
M44: ⓘ Each bar fills toward its goal. They move on their own as your savings and inputs change.
B60: Breakdown helper (used by the doughnut)
B61: Rent | C61: =SUMPRODUCT((Fixed_Name="Rent")*Fixed_Amt*(Fixed_Start<=Sel_Month))
B62: Phone | C62: =SUMPRODUCT((Fixed_Name="Phone (Rogers)")*Fixed_Amt*(Fixed_Start<=Sel_Month))
B63: India loan | C63: =SUMPRODUCT((Fixed_Name="India loan payment")*Fixed_Amt*(Fixed_Start<=Sel_Month))
B64: Groceries | C64: =SUMPRODUCT((Fixed_Name="Groceries")*Fixed_Amt*(Fixed_Start<=Sel_Month))
B65: Misc | C65: =SUMPRODUCT((Fixed_Name="Miscellaneous")*Fixed_Amt*(Fixed_Start<=Sel_Month))
B66: Subscriptions | C66: =INDEX(MonthData!$I$2:$I$13,MATCH(Sel_Label,Month_Labels,0))
B67: Extras | C67: =INDEX(MonthData!$H$2:$H$13,MATCH(Sel_Label,Month_Labels,0))

Sheet Income
C2: INCOME
C3: Your job, your real paycheques, and government money — all in one place.
B5: PAYCHEQUE ESTIMATOR
B6: ⓘ Type into the gold cells only. It estimates your 2-week take-home. The real Paycheque Log below is what the dashboard actually trusts.
B8: Pay rate (per hour) | D8: 21.3 | H8: SANITY CHECK — MONTHLY TAKE-HOME
B9: Hours worked (2-week period) | D9: 83 | H9: Weekly hours | J9: ≈ Monthly
B10: Overtime hours (after 44/wk — rare) | D10: 0 | H10: 20 hrs | J10: $1,610
B11: Overtime rate (per hour) | D11: 31.95 | H11: 24 hrs | J11: $1,880
B12: Income tax % (match your stub) | D12: 0.05 | H12: 30 hrs | J12: $2,265
B13: Base pay | D13: =Pay_Rate*Est_Hours | H13: 35 hrs | J13: $2,590
B14: Vacation pay (4%) | D14: =(Pay_Rate*Est_Hours)*0.04 | H14: 40 hrs | J14: $2,915
B15: Overtime pay | D15: =Est_OT*OT_Rate
B16: Gross pay | D16: =D13+D14+D15
B17: Less: CPP (5.95% over $134.62) | D17: =-MAX(0,(D16-134.62)*0.0595)
B18: Less: EI (1.63%) | D18: =-D16*0.0163
B19: Less: Union dues (1.57%) | D19: =-D16*0.0157
B20: Less: Income tax | D20: =-D16*Tax_Pct
B21: ESTIMATED TAKE-HOME (2 weeks) | D21: =D16+D17+D18+D19+D20
B24: PAYCHEQUE LOG — TYPE EACH REAL PAYCHEQUE HERE
B25: ⓘ This is the most important table. Each payday, type the DATE and the NET amount from your real pay stub. The dashboard adds these up automatically.
B26: Date paid | C26: Hours | D26: Net amount (CAD) | E26: Notes
B27: 46176 | C27: 24 | D27: 423.7 | E27: First short cheque
B28: 46190 | C28: 83 | D28: 1521 | E28: 83 hrs this period
B51: TOTAL LOGGED (all time) | D51: =SUM(D27:D50)
B54: GOVERNMENT MONEY (EXTRA INCOME, ADDED AUTOMATICALLY)
B55: ⓘ These top up your monthly income on the dashboard. 'Interval' is the math switch: 0 = one-time, 1 = every month, 3 = every quarter. Leave it as set.
B56: Payment | C56: Amount | D56: Starts | E56: How often | F56: Interval
B57: Tax refund (one-time) | C57: 1211.65 | D57: 46174 | E57: One-time | F57: 0
B58: CGEB top-up (one-time) | C58: 174.5 | D58: 46174 | E58: One-time | F58: 0
B59: CGEB (quarterly) | C59: 169.75 | D59: 46204 | E59: Every quarter | F59: 3
B60: OTB (monthly) | C60: 71.95 | D60: 46204 | E60: Every month | F60: 1

Sheet Expenses
C2: EXPENSES
C3: Your fixed monthly bills, plus a takeout/spending log so you can watch it add up.
B5: FIXED MONTHLY BILLS
B6: ⓘ Type the amount and the month it starts. 'Starts' lets a bill begin later — your India loan starts Jul 2026. Leave older bills at Jan 2020 to mean 'always on'.
B7: Bill | C7: Amount | D7: Starts | E7: Notes
B8: Rent | C8: 600 | D8: 43831 | E8: Paid ~28th–29th of prior month
B9: Phone (Rogers) | C9: 103.28 | D9: 43831 | E9: Around the 8th–9th
B10: India loan payment | C10: 334 | D10: 46204 | E10: Starts Jul 2026 — see Debt sheet
B11: Groceries | C11: 100 | D11: 43831 | E11: Monthly budget
B12: Miscellaneous | C12: 50 | D12: 43831 | E12: Buffer for small stuff
B16: TOTAL FIXED / MONTH | C16: =SUM(C8:C15)
B18: SPENDING TO WATCH — TAKEOUT & EXTRAS LOG
B19: ⓘ Every time you spend on takeout or extras, add a line. The bar below fills up against your $100 grocery budget so you SEE it adding up.
B20: Date | C20: Category | D20: Amount | E20: Note | H20: THIS MONTH vs $100 BUDGET
B21: 46175 | C21: Takeout/Dining | D21: 68.9 | E21: Big takeout day | H21: =SUMIFS(Disc_Amt,Disc_Date,">="&Sel_Month,Disc_Date,"<"&EDATE(Sel_Month,1))
H22: spent on extras this month
H24: Budget used
H25: =MIN(1,H21/100)
H26: (over 100% = past your grocery budget)
B45: TOTAL LOGGED (all time) | D45: =SUM(D21:D44)

Sheet Bills & Subscriptions
C2: BILLS & SUBSCRIPTIONS
C3: Tick each one off when it's paid. All amounts in Canadian dollars ($).
B5: RECURRING BILLS & SUBSCRIPTIONS
B6: ⓘ Tick the gold box under a month once you've paid it. 'In budget?' = Yes feeds the dashboard; set it to No for bills already counted on the Expenses sheet (like rent & phone) so nothing is double-counted.
B7: Bill / Subscription | C7: Amount | D7: Due day | E7: In budget? | F7: Starts | G7: Jun'26 | H7: Jul'26 | I7: Aug'26 | J7: Sep'26 | K7: Oct'26 | L7: Nov'26 | M7: Dec'26 | N7: Jan'27 | O7: Feb'27 | P7: Mar'27 | Q7: Apr'27 | R7: May'27 | S7: Annual
B8: Phone (Rogers) | C8: 103.28 | D8: 9 | E8: No | F8: 46174 | S8: =IF(C8="","",C8*12)
B9: Claude AI | C9: 31.64 | D9: 5 | E9: Yes | F9: 46174 | S9: =IF(C9="","",C9*12)
S10: =IF(C10="","",C10*12)
S11: =IF(C11="","",C11*12)
S12: =IF(C12="","",C12*12)
S13: =IF(C13="","",C13*12)
S14: =IF(C14="","",C14*12)
S15: =IF(C15="","",C15*12)
S16: =IF(C16="","",C16*12)
S17: =IF(C17="","",C17*12)
S18: =IF(C18="","",C18*12)
S19: =IF(C19="","",C19*12)
B20: ANNUAL TOTAL (all rows) | S20: =SUM(S8:S19)
B22: SHORT-TERM PAYMENT PLANS (FINISH ON A DATE)
B23: ⓘ Interest-free plans that end. The perfume plan is pre-loaded. The 'Finish date' updates from the last dated row automatically.
B24: Plan / Item | C24: Date | D24: Amount | E24: Paid?
B25: Perfume payment plan | C25: 46178 | D25: 60.4 | E25: ✓
B26: Perfume payment plan | C26: 46192 | D26: 60.4
B27: Perfume payment plan | C27: 46206 | D27: 60.4
B28: Perfume payment plan | C28: 46220 | D28: 60.38
B31: PLAN TOTAL | D31: =SUM(D25:D30)
B32: Finishes on | D32: =IF(COUNT(C25:C30)=0,"—",MAX(C25:C30))
B34: MONTHLY BILL CALENDAR
B35: Show month: | C35: 46174 | E35: =TEXT(Cal_Month,"mmmm yyyy")
B36: ⓘ Days with a bill due are highlighted pink (matched from the 'Due day' column above). Change the month to see another month.
C37: Sun | D37: Mon | E37: Tue | F37: Wed | G37: Thu | H37: Fri | I37: Sat
C38: =IF(MONTH(Cal_Month-WEEKDAY(Cal_Month)+1+0)=MONTH(Cal_Month),DAY(Cal_Month-WEEKDAY(Cal_Month)+1+0),"") | D38: =IF(MONTH(Cal_Month-WEEKDAY(Cal_Month)+1+1)=MONTH(Cal_Month),DAY(Cal_Month-WEEKDAY(Cal_Month)+1+1),"") | E38: =IF(MONTH(Cal_Month-WEEKDAY(Cal_Month)+1+2)=MONTH(Cal_Month),DAY(Cal_Month-WEEKDAY(Cal_Month)+1+2),"") | F38: =IF(MONTH(Cal_Month-WEEKDAY(Cal_Month)+1+3)=MONTH(Cal_Month),DAY(Cal_Month-WEEKDAY(Cal_Month)+1+3),"") | G38: =IF(MONTH(Cal_Month-WEEKDAY(Cal_Month)+1+4)=MONTH(Cal_Month),DAY(Cal_Month-WEEKDAY(Cal_Month)+1+4),"") | H38: =IF(MONTH(Cal_Month-WEEKDAY(Cal_Month)+1+5)=MONTH(Cal_Month),DAY(Cal_Month-WEEKDAY(Cal_Month)+1+5),"") | I38: =IF(MONTH(Cal_Month-WEEKDAY(Cal_Month)+1+6)=MONTH(Cal_Month),DAY(Cal_Month-WEEKDAY(Cal_Month)+1+6),"")
C39: =IF(MONTH(Cal_Month-WEEKDAY(Cal_Month)+1+7)=MONTH(Cal_Month),DAY(Cal_Month-WEEKDAY(Cal_Month)+1+7),"") | D39: =IF(MONTH(Cal_Month-WEEKDAY(Cal_Month)+1+8)=MONTH(Cal_Month),DAY(Cal_Month-WEEKDAY(Cal_Month)+1+8),"") | E39: =IF(MONTH(Cal_Month-WEEKDAY(Cal_Month)+1+9)=MONTH(Cal_Month),DAY(Cal_Month-WEEKDAY(Cal_Month)+1+9),"") | F39: =IF(MONTH(Cal_Month-WEEKDAY(Cal_Month)+1+10)=MONTH(Cal_Month),DAY(Cal_Month-WEEKDAY(Cal_Month)+1+10),"") | G39: =IF(MONTH(Cal_Month-WEEKDAY(Cal_Month)+1+11)=MONTH(Cal_Month),DAY(Cal_Month-WEEKDAY(Cal_Month)+1+11),"") | H39: =IF(MONTH(Cal_Month-WEEKDAY(Cal_Month)+1+12)=MONTH(Cal_Month),DAY(Cal_Month-WEEKDAY(Cal_Month)+1+12),"") | I39: =IF(MONTH(Cal_Month-WEEKDAY(Cal_Month)+1+13)=MONTH(Cal_Month),DAY(Cal_Month-WEEKDAY(Cal_Month)+1+13),"")
C40: =IF(MONTH(Cal_Month-WEEKDAY(Cal_Month)+1+14)=MONTH(Cal_Month),DAY(Cal_Month-WEEKDAY(Cal_Month)+1+14),"") | D40: =IF(MONTH(Cal_Month-WEEKDAY(Cal_Month)+1+15)=MONTH(Cal_Month),DAY(Cal_Month-WEEKDAY(Cal_Month)+1+15),"") | E40: =IF(MONTH(Cal_Month-WEEKDAY(Cal_Month)+1+16)=MONTH(Cal_Month),DAY(Cal_Month-WEEKDAY(Cal_Month)+1+16),"") | F40: =IF(MONTH(Cal_Month-WEEKDAY(Cal_Month)+1+17)=MONTH(Cal_Month),DAY(Cal_Month-WEEKDAY(Cal_Month)+1+17),"") | G40: =IF(MONTH(Cal_Month-WEEKDAY(Cal_Month)+1+18)=MONTH(Cal_Month),DAY(Cal_Month-WEEKDAY(Cal_Month)+1+18),"") | H40: =IF(MONTH(Cal_Month-WEEKDAY(Cal_Month)+1+19)=MONTH(Cal_Month),DAY(Cal_Month-WEEKDAY(Cal_Month)+1+19),"") | I40: =IF(MONTH(Cal_Month-WEEKDAY(Cal_Month)+1+20)=MONTH(Cal_Month),DAY(Cal_Month-WEEKDAY(Cal_Month)+1+20),"")
C41: =IF(MONTH(Cal_Month-WEEKDAY(Cal_Month)+1+21)=MONTH(Cal_Month),DAY(Cal_Month-WEEKDAY(Cal_Month)+1+21),"") | D41: =IF(MONTH(Cal_Month-WEEKDAY(Cal_Month)+1+22)=MONTH(Cal_Month),DAY(Cal_Month-WEEKDAY(Cal_Month)+1+22),"") | E41: =IF(MONTH(Cal_Month-WEEKDAY(Cal_Month)+1+23)=MONTH(Cal_Month),DAY(Cal_Month-WEEKDAY(Cal_Month)+1+23),"") | F41: =IF(MONTH(Cal_Month-WEEKDAY(Cal_Month)+1+24)=MONTH(Cal_Month),DAY(Cal_Month-WEEKDAY(Cal_Month)+1+24),"") | G41: =IF(MONTH(Cal_Month-WEEKDAY(Cal_Month)+1+25)=MONTH(Cal_Month),DAY(Cal_Month-WEEKDAY(Cal_Month)+1+25),"") | H41: =IF(MONTH(Cal_Month-WEEKDAY(Cal_Month)+1+26)=MONTH(Cal_Month),DAY(Cal_Month-WEEKDAY(Cal_Month)+1+26),"") | I41: =IF(MONTH(Cal_Month-WEEKDAY(Cal_Month)+1+27)=MONTH(Cal_Month),DAY(Cal_Month-WEEKDAY(Cal_Month)+1+27),"")
C42: =IF(MONTH(Cal_Month-WEEKDAY(Cal_Month)+1+28)=MONTH(Cal_Month),DAY(Cal_Month-WEEKDAY(Cal_Month)+1+28),"") | D42: =IF(MONTH(Cal_Month-WEEKDAY(Cal_Month)+1+29)=MONTH(Cal_Month),DAY(Cal_Month-WEEKDAY(Cal_Month)+1+29),"") | E42: =IF(MONTH(Cal_Month-WEEKDAY(Cal_Month)+1+30)=MONTH(Cal_Month),DAY(Cal_Month-WEEKDAY(Cal_Month)+1+30),"") | F42: =IF(MONTH(Cal_Month-WEEKDAY(Cal_Month)+1+31)=MONTH(Cal_Month),DAY(Cal_Month-WEEKDAY(Cal_Month)+1+31),"") | G42: =IF(MONTH(Cal_Month-WEEKDAY(Cal_Month)+1+32)=MONTH(Cal_Month),DAY(Cal_Month-WEEKDAY(Cal_Month)+1+32),"") | H42: =IF(MONTH(Cal_Month-WEEKDAY(Cal_Month)+1+33)=MONTH(Cal_Month),DAY(Cal_Month-WEEKDAY(Cal_Month)+1+33),"") | I42: =IF(MONTH(Cal_Month-WEEKDAY(Cal_Month)+1+34)=MONTH(Cal_Month),DAY(Cal_Month-WEEKDAY(Cal_Month)+1+34),"")
C43: =IF(MONTH(Cal_Month-WEEKDAY(Cal_Month)+1+35)=MONTH(Cal_Month),DAY(Cal_Month-WEEKDAY(Cal_Month)+1+35),"") | D43: =IF(MONTH(Cal_Month-WEEKDAY(Cal_Month)+1+36)=MONTH(Cal_Month),DAY(Cal_Month-WEEKDAY(Cal_Month)+1+36),"") | E43: =IF(MONTH(Cal_Month-WEEKDAY(Cal_Month)+1+37)=MONTH(Cal_Month),DAY(Cal_Month-WEEKDAY(Cal_Month)+1+37),"") | F43: =IF(MONTH(Cal_Month-WEEKDAY(Cal_Month)+1+38)=MONTH(Cal_Month),DAY(Cal_Month-WEEKDAY(Cal_Month)+1+38),"") | G43: =IF(MONTH(Cal_Month-WEEKDAY(Cal_Month)+1+39)=MONTH(Cal_Month),DAY(Cal_Month-WEEKDAY(Cal_Month)+1+39),"") | H43: =IF(MONTH(Cal_Month-WEEKDAY(Cal_Month)+1+40)=MONTH(Cal_Month),DAY(Cal_Month-WEEKDAY(Cal_Month)+1+40),"") | I43: =IF(MONTH(Cal_Month-WEEKDAY(Cal_Month)+1+41)=MONTH(Cal_Month),DAY(Cal_Month-WEEKDAY(Cal_Month)+1+41),"")

Sheet Debt Tracker
C2: DEBT TRACKER
C3: Pay the Avion in full every month. Build your emergency fund, then crush the 12% India loan.
B5: INDIA EDUCATION LOAN — CURRENCY CONVERTER | J5: RBC AVION VISA
B6: ⓘ Type the rupee amounts and today's exchange rate (how many rupees per $1 CAD). The CAD figures update by themselves. | J6: Credit limit | L6: 1000
B7: Still owed (₹ INR) | C7: 1500000 | E7: → in CAD: | F7: =INR_Owed/INR_per_CAD | J7: Interest if unpaid | L7: 0.1999
B8: Exchange rate (₹ per $1 CAD) | C8: 62 | J8: Balance carried (should be $0) | L8: 0
B9: Monthly payment (₹ INR) | C9: 23338 | E9: → in CAD: | F9: =INR_Pay/INR_per_CAD | J9: =IF(Avion_Bal>0,"⚠ PAY THIS OFF — 19.99% is costing you money!","✓ Paid in full — nice work")
B10: Interest rate (per year) | C10: 0.12
B11: ⓘ Your India loan is 12%/yr — that's expensive. Once your emergency fund is built, this is the #1 thing to attack.
B13: DEBT OVERVIEW (UP TO 12 DEBTS)
B14: ⓘ India & Avion fill in from the boxes above. For any other debt, type into the gold cells. 'Months left' and 'Debt-free date' calculate from your payment.
B15: Debt | C15: Amount owed (CAD) | D15: Interest | E15: Start date | F15: Min monthly (CAD) | G15: Months left | H15: Debt-free date | Q15: Year | R15: Projected debt
B16: India education loan | C16: =India_CAD | D16: =India_Rate | E16: 46204 | F16: =India_Pay | G16: =IF(N(C16)<=0,"",IF(F16<=C16*(D16/12),"⚠ raise pay",ROUNDUP(NPER(D16/12,-F16,C16),0))) | H16: =IF(ISNUMBER(G16),EDATE(TODAY(),G16),"—") | Q16: Y0 | R16: =MAX(0,India_CAD*(1+India_Rate/12)^0-India_Pay*(((1+India_Rate/12)^0)-1)/(India_Rate/12))+SUM(C17:C27)
B17: RBC Avion Visa | C17: =Avion_Bal | D17: 0.1999 | E17: 45261 | F17: 0 | G17: =IF(N(C17)<=0,"",IF(F17<=C17*(D17/12),"⚠ raise pay",ROUNDUP(NPER(D17/12,-F17,C17),0))) | H17: =IF(ISNUMBER(G17),EDATE(TODAY(),G17),"—") | Q17: Y1 | R17: =MAX(0,India_CAD*(1+India_Rate/12)^12-India_Pay*(((1+India_Rate/12)^12)-1)/(India_Rate/12))+SUM(C17:C27)
G18: =IF(N(C18)<=0,"",IF(F18<=C18*(D18/12),"⚠ raise pay",ROUNDUP(NPER(D18/12,-F18,C18),0))) | H18: =IF(ISNUMBER(G18),EDATE(TODAY(),G18),"—") | Q18: Y2 | R18: =MAX(0,India_CAD*(1+India_Rate/12)^24-India_Pay*(((1+India_Rate/12)^24)-1)/(India_Rate/12))+SUM(C17:C27)
G19: =IF(N(C19)<=0,"",IF(F19<=C19*(D19/12),"⚠ raise pay",ROUNDUP(NPER(D19/12,-F19,C19),0))) | H19: =IF(ISNUMBER(G19),EDATE(TODAY(),G19),"—") | Q19: Y3 | R19: =MAX(0,India_CAD*(1+India_Rate/12)^36-India_Pay*(((1+India_Rate/12)^36)-1)/(India_Rate/12))+SUM(C17:C27)
G20: =IF(N(C20)<=0,"",IF(F20<=C20*(D20/12),"⚠ raise pay",ROUNDUP(NPER(D20/12,-F20,C20),0))) | H20: =IF(ISNUMBER(G20),EDATE(TODAY(),G20),"—") | Q20: Y4 | R20: =MAX(0,India_CAD*(1+India_Rate/12)^48-India_Pay*(((1+India_Rate/12)^48)-1)/(India_Rate/12))+SUM(C17:C27)
G21: =IF(N(C21)<=0,"",IF(F21<=C21*(D21/12),"⚠ raise pay",ROUNDUP(NPER(D21/12,-F21,C21),0))) | H21: =IF(ISNUMBER(G21),EDATE(TODAY(),G21),"—") | Q21: Y5 | R21: =MAX(0,India_CAD*(1+India_Rate/12)^60-India_Pay*(((1+India_Rate/12)^60)-1)/(India_Rate/12))+SUM(C17:C27)
G22: =IF(N(C22)<=0,"",IF(F22<=C22*(D22/12),"⚠ raise pay",ROUNDUP(NPER(D22/12,-F22,C22),0))) | H22: =IF(ISNUMBER(G22),EDATE(TODAY(),G22),"—") | Q22: Y6 | R22: =MAX(0,India_CAD*(1+India_Rate/12)^72-India_Pay*(((1+India_Rate/12)^72)-1)/(India_Rate/12))+SUM(C17:C27)
G23: =IF(N(C23)<=0,"",IF(F23<=C23*(D23/12),"⚠ raise pay",ROUNDUP(NPER(D23/12,-F23,C23),0))) | H23: =IF(ISNUMBER(G23),EDATE(TODAY(),G23),"—") | Q23: Y7 | R23: =MAX(0,India_CAD*(1+India_Rate/12)^84-India_Pay*(((1+India_Rate/12)^84)-1)/(India_Rate/12))+SUM(C17:C27)
G24: =IF(N(C24)<=0,"",IF(F24<=C24*(D24/12),"⚠ raise pay",ROUNDUP(NPER(D24/12,-F24,C24),0))) | H24: =IF(ISNUMBER(G24),EDATE(TODAY(),G24),"—") | Q24: Y8 | R24: =MAX(0,India_CAD*(1+India_Rate/12)^96-India_Pay*(((1+India_Rate/12)^96)-1)/(India_Rate/12))+SUM(C17:C27)
G25: =IF(N(C25)<=0,"",IF(F25<=C25*(D25/12),"⚠ raise pay",ROUNDUP(NPER(D25/12,-F25,C25),0))) | H25: =IF(ISNUMBER(G25),EDATE(TODAY(),G25),"—") | Q25: Y9 | R25: =MAX(0,India_CAD*(1+India_Rate/12)^108-India_Pay*(((1+India_Rate/12)^108)-1)/(India_Rate/12))+SUM(C17:C27)
G26: =IF(N(C26)<=0,"",IF(F26<=C26*(D26/12),"⚠ raise pay",ROUNDUP(NPER(D26/12,-F26,C26),0))) | H26: =IF(ISNUMBER(G26),EDATE(TODAY(),G26),"—") | Q26: Y10 | R26: =MAX(0,India_CAD*(1+India_Rate/12)^120-India_Pay*(((1+India_Rate/12)^120)-1)/(India_Rate/12))+SUM(C17:C27)
G27: =IF(N(C27)<=0,"",IF(F27<=C27*(D27/12),"⚠ raise pay",ROUNDUP(NPER(D27/12,-F27,C27),0))) | H27: =IF(ISNUMBER(G27),EDATE(TODAY(),G27),"—") | Q27: Y11 | R27: =MAX(0,India_CAD*(1+India_Rate/12)^132-India_Pay*(((1+India_Rate/12)^132)-1)/(India_Rate/12))+SUM(C17:C27)
B28: TOTAL DEBT / DEBT-FREE DATE | C28: =SUM(C16:C27) | H28: =IFERROR(EDATE(TODAY(),MAX(IF(ISNUMBER(G16:G27),G16:G27))),"—") | Q28: Y12 | R28: =MAX(0,India_CAD*(1+India_Rate/12)^144-India_Pay*(((1+India_Rate/12)^144)-1)/(India_Rate/12))+SUM(C17:C27)
B30: DEBT GOING DOWN OVER TIME | J30: CURRENT BALANCES | O30: MONTHS LEFT

Sheet Savings & Goals
C2: SAVINGS & GOALS
C3: Your accounts and the goals you're saving toward. Type into gold cells only.
B5: ACCOUNTS
B6: ⓘ Update each balance whenever you check your apps. The $25 Saven membership share is NOT real savings, so it is shown separately and left out of every total.
B7: Account | C7: Balance | D7: Rate / Auto | E7: This month's interest | F7: Notes
B8: Saven HISA (emergency fund) | C8: 300 | D8: 0.0285 | E8: =C8*D8/12 | F8: Main emergency fund — earns interest
B9: • Membership share (not savings) | C9: 25 | D9: — | E9: — | F9: One-time, no interest, excluded from totals
B10: Wealthsimple TFSA (XEQT) | C10: 100 | D10: 10 | E10: auto | F10: Long-term (5+ yrs). $ auto-invested monthly
B11: Wealthsimple HISA | C11: 0 | D11: — | E11: — | F11: Spare HISA
B12: RBC chequing | C12: 500 | D12: — | E12: — | F12: Everyday account (usually $300–$700)
B13: TOTAL SAVINGS (excl. membership share) | C13: =Saven_Bal+WS_TFSA+WS_HISA+RBC_Chq | D13: Saven + TFSA + WS HISA + chequing
B16: GOALS
B17: ⓘ Type your Target and your planned $/month (gold). The progress, the amount you still need each month, and the projected finish all calculate themselves.
B18: Goal | C18: Target | D18: Saved now | E18: Plan $/mo | F18: Progress | G18: Need $/mo | H18: Finish by | I18: On track?
B19: Emergency fund (3mo $3,600 → 6mo $7,150) | C19: 7150 | D19: =Saven_Bal | E19: 200 | F19: =D19/C19 | G19: ="—" | H19: =IF(E19<=0,"add plan",EDATE(TODAY(),ROUNDUP((C19-D19)/E19,0))) | I19: =IF(D19>=C19,"Done",IF(D19>=3600,"6mo next","build 3mo"))
B20: $7,000 total savings by Dec 2026 | C20: 7000 | D20: =Sav_Total | E20: 300 | F20: =D20/C20 | G20: =MAX(0,(C20-D20)/MAX(1,DATEDIF(TODAY(),DATE(2026,12,1),"m"))) | H20: =DATE(2026,12,1) | I20: =IF(D20+E20*MAX(1,DATEDIF(TODAY(),DATE(2026,12,1),"m"))>=C20,"Yes","No")
B21: India trip fund (~Jan 2027) | C21: 5000 | D21: 0 | E21: 150 | F21: =D21/C21 | G21: =MAX(0,(C21-D21)/MAX(1,DATEDIF(TODAY(),DATE(2027,1,1),"m"))) | H21: =DATE(2027,1,1) | I21: =IF(D21+E21*MAX(1,DATEDIF(TODAY(),DATE(2027,1,1),"m"))>=C21,"On track","Behind")
B24: WHERE YOUR SAVINGS SIT
B55: helper
B56: Saven (emergency) | C56: =Saven_Bal
B57: WS TFSA (long-term) | C57: =WS_TFSA
B58: WS HISA | C58: =WS_HISA
B59: RBC chequing | C59: =RBC_Chq

Sheet Net Worth
C2: NET WORTH TRACKER
C3: Everything you own minus everything you owe. It updates from your other sheets.
B5: TOTAL NET WORTH | G5: NET WORTH GOAL | L5: AMOUNT TO GOAL
B6: =Sav_Total-(India_CAD+Avion_Bal) | G6: =NW_Goal | L6: =NW_Goal-(Sav_Total-(India_CAD+Avion_Bal))
B9: Set your custom net worth goal → | E9: 25000
B12: NET WORTH OVER TIME | K12: ASSETS DISTRIBUTION
B31: ASSETS VS LIABILITIES | K31: LIABILITIES DISTRIBUTION
B51: helper (assets vs liabilities by month) | L51: Month | M51: Assets | N51: Liabilities | O51: Net worth
L52: =MonthData!B2 | M52: =Sav_Total+MonthData!L2 | N52: =MAX(0,(India_CAD+Avion_Bal)-India_Pay*1) | O52: =M52-N52
L53: =MonthData!B3 | M53: =Sav_Total+MonthData!L3 | N53: =MAX(0,(India_CAD+Avion_Bal)-India_Pay*2) | O53: =M53-N53
L54: =MonthData!B4 | M54: =Sav_Total+MonthData!L4 | N54: =MAX(0,(India_CAD+Avion_Bal)-India_Pay*3) | O54: =M54-N54
L55: =MonthData!B5 | M55: =Sav_Total+MonthData!L5 | N55: =MAX(0,(India_CAD+Avion_Bal)-India_Pay*4) | O55: =M55-N55
L56: =MonthData!B6 | M56: =Sav_Total+MonthData!L6 | N56: =MAX(0,(India_CAD+Avion_Bal)-India_Pay*5) | O56: =M56-N56
L57: =MonthData!B7 | M57: =Sav_Total+MonthData!L7 | N57: =MAX(0,(India_CAD+Avion_Bal)-India_Pay*6) | O57: =M57-N57
L58: =MonthData!B8 | M58: =Sav_Total+MonthData!L8 | N58: =MAX(0,(India_CAD+Avion_Bal)-India_Pay*7) | O58: =M58-N58
L59: =MonthData!B9 | M59: =Sav_Total+MonthData!L9 | N59: =MAX(0,(India_CAD+Avion_Bal)-India_Pay*8) | O59: =M59-N59
B60: Saven | C60: =Saven_Bal | E60: India loan | F60: =India_CAD | L60: =MonthData!B10 | M60: =Sav_Total+MonthData!L10 | N60: =MAX(0,(India_CAD+Avion_Bal)-India_Pay*9) | O60: =M60-N60
B61: WS TFSA | C61: =WS_TFSA | E61: Avion card | F61: =Avion_Bal | L61: =MonthData!B11 | M61: =Sav_Total+MonthData!L11 | N61: =MAX(0,(India_CAD+Avion_Bal)-India_Pay*10) | O61: =M61-N61
B62: RBC chequing | C62: =RBC_Chq | L62: =MonthData!B12 | M62: =Sav_Total+MonthData!L12 | N62: =MAX(0,(India_CAD+Avion_Bal)-India_Pay*11) | O62: =M62-N62
B63: WS HISA | C63: =WS_HISA | L63: =MonthData!B13 | M63: =Sav_Total+MonthData!L13 | N63: =MAX(0,(India_CAD+Avion_Bal)-India_Pay*12) | O63: =M63-N63

Sheet Side Income
C2: SIDE INCOME
C3: Freelance & content income — set up and ready for when you start earning.
B5: TOTAL SIDE INCOME | F5: TOTAL SIDE EXPENSES | J5: NET PROFIT
B6: =SUM(Side_Inc_Amt) | F6: =SUM(Side_Exp_Amt) | J6: =SUM(Side_Inc_Amt)-SUM(Side_Exp_Amt)
B9: INCOME LOG | G9: EXPENSE LOG
B10: ⓘ Log every paid gig here. Pick a category from the dropdown. | G10: ⓘ Costs tied to this work — software, gear, subscriptions.
B11: Date | C11: Client / Source | D11: Category | E11: Amount | G11: Date | H11: Description | I11: Category | J11: Amount
B26: ⓘ This sheet sits mostly empty until you start earning — that's fine, it's ready to go.
B34: TOTAL INCOME | E34: =SUM(E12:E33) | G34: TOTAL EXPENSES | J34: =SUM(J12:J33)
B36: MONTHLY SUMMARY
L37: Month | M37: Income | N37: Expense | O37: Profit
L38: 46174 | M38: =SUMIFS(Side_Inc_Amt,Side_Inc_Date,">="&L38,Side_Inc_Date,"<"&EDATE(L38,1)) | N38: =SUMIFS(Side_Exp_Amt,Side_Exp_Date,">="&L38,Side_Exp_Date,"<"&EDATE(L38,1)) | O38: =M38-N38
L39: 46204 | M39: =SUMIFS(Side_Inc_Amt,Side_Inc_Date,">="&L39,Side_Inc_Date,"<"&EDATE(L39,1)) | N39: =SUMIFS(Side_Exp_Amt,Side_Exp_Date,">="&L39,Side_Exp_Date,"<"&EDATE(L39,1)) | O39: =M39-N39
L40: 46235 | M40: =SUMIFS(Side_Inc_Amt,Side_Inc_Date,">="&L40,Side_Inc_Date,"<"&EDATE(L40,1)) | N40: =SUMIFS(Side_Exp_Amt,Side_Exp_Date,">="&L40,Side_Exp_Date,"<"&EDATE(L40,1)) | O40: =M40-N40
L41: 46266 | M41: =SUMIFS(Side_Inc_Amt,Side_Inc_Date,">="&L41,Side_Inc_Date,"<"&EDATE(L41,1)) | N41: =SUMIFS(Side_Exp_Amt,Side_Exp_Date,">="&L41,Side_Exp_Date,"<"&EDATE(L41,1)) | O41: =M41-N41
L42: 46296 | M42: =SUMIFS(Side_Inc_Amt,Side_Inc_Date,">="&L42,Side_Inc_Date,"<"&EDATE(L42,1)) | N42: =SUMIFS(Side_Exp_Amt,Side_Exp_Date,">="&L42,Side_Exp_Date,"<"&EDATE(L42,1)) | O42: =M42-N42
L43: 46327 | M43: =SUMIFS(Side_Inc_Amt,Side_Inc_Date,">="&L43,Side_Inc_Date,"<"&EDATE(L43,1)) | N43: =SUMIFS(Side_Exp_Amt,Side_Exp_Date,">="&L43,Side_Exp_Date,"<"&EDATE(L43,1)) | O43: =M43-N43
L44: 46357 | M44: =SUMIFS(Side_Inc_Amt,Side_Inc_Date,">="&L44,Side_Inc_Date,"<"&EDATE(L44,1)) | N44: =SUMIFS(Side_Exp_Amt,Side_Exp_Date,">="&L44,Side_Exp_Date,"<"&EDATE(L44,1)) | O44: =M44-N44
L45: 46388 | M45: =SUMIFS(Side_Inc_Amt,Side_Inc_Date,">="&L45,Side_Inc_Date,"<"&EDATE(L45,1)) | N45: =SUMIFS(Side_Exp_Amt,Side_Exp_Date,">="&L45,Side_Exp_Date,"<"&EDATE(L45,1)) | O45: =M45-N45
L46: 46419 | M46: =SUMIFS(Side_Inc_Amt,Side_Inc_Date,">="&L46,Side_Inc_Date,"<"&EDATE(L46,1)) | N46: =SUMIFS(Side_Exp_Amt,Side_Exp_Date,">="&L46,Side_Exp_Date,"<"&EDATE(L46,1)) | O46: =M46-N46
L47: 46447 | M47: =SUMIFS(Side_Inc_Amt,Side_Inc_Date,">="&L47,Side_Inc_Date,"<"&EDATE(L47,1)) | N47: =SUMIFS(Side_Exp_Amt,Side_Exp_Date,">="&L47,Side_Exp_Date,"<"&EDATE(L47,1)) | O47: =M47-N47
L48: 46478 | M48: =SUMIFS(Side_Inc_Amt,Side_Inc_Date,">="&L48,Side_Inc_Date,"<"&EDATE(L48,1)) | N48: =SUMIFS(Side_Exp_Amt,Side_Exp_Date,">="&L48,Side_Exp_Date,"<"&EDATE(L48,1)) | O48: =M48-N48
L49: 46508 | M49: =SUMIFS(Side_Inc_Amt,Side_Inc_Date,">="&L49,Side_Inc_Date,"<"&EDATE(L49,1)) | N49: =SUMIFS(Side_Exp_Amt,Side_Exp_Date,">="&L49,Side_Exp_Date,"<"&EDATE(L49,1)) | O49: =M49-N49

Sheet Habit Tracker
C2: HABIT TRACKER
C3: Tick a box each day you do the habit. The % and charts update on their own.
B4: Show month: | C4: 46174 | G4: =TEXT(Habit_Month,"mmmm yyyy")
B5: ⓘ Days past the end of the month don't count. The % uses the real number of days in the month you picked.
B7: Habit | C7: 1 | D7: 2 | E7: 3 | F7: 4 | G7: 5 | H7: 6 | I7: 7 | J7: 8 | K7: 9 | L7: 10 | M7: 11 | N7: 12 | O7: 13 | P7: 14 | Q7: 15 | R7: 16 | S7: 17 | T7: 18 | U7: 19 | V7: 20 | W7: 21 | X7: 22 | Y7: 23 | Z7: 24 | AA7: 25 | AB7: 26 | AC7: 27 | AD7: 28 | AE7: 29 | AF7: 30 | AG7: 31 | AH7: % done
B8: Gym / workout | AH8: =IF(B8="","",COUNTIF(C8:AG8,"✓")/DAY(EOMONTH(Habit_Month,0)))
B9: Post content | AH9: =IF(B9="","",COUNTIF(C9:AG9,"✓")/DAY(EOMONTH(Habit_Month,0)))
B10: No-spend day | AH10: =IF(B10="","",COUNTIF(C10:AG10,"✓")/DAY(EOMONTH(Habit_Month,0)))
AH11: =IF(B11="","",COUNTIF(C11:AG11,"✓")/DAY(EOMONTH(Habit_Month,0)))
AH12: =IF(B12="","",COUNTIF(C12:AG12,"✓")/DAY(EOMONTH(Habit_Month,0)))
AH13: =IF(B13="","",COUNTIF(C13:AG13,"✓")/DAY(EOMONTH(Habit_Month,0)))
AH14: =IF(B14="","",COUNTIF(C14:AG14,"✓")/DAY(EOMONTH(Habit_Month,0)))
AH15: =IF(B15="","",COUNTIF(C15:AG15,"✓")/DAY(EOMONTH(Habit_Month,0)))
B17: COMPLETION % BY HABIT | L17: DAILY ACTIVITY
B39: daily totals helper
C40: 1 | D40: 2 | E40: 3 | F40: 4 | G40: 5 | H40: 6 | I40: 7 | J40: 8 | K40: 9 | L40: 10 | M40: 11 | N40: 12 | O40: 13 | P40: 14 | Q40: 15 | R40: 16 | S40: 17 | T40: 18 | U40: 19 | V40: 20 | W40: 21 | X40: 22 | Y40: 23 | Z40: 24 | AA40: 25 | AB40: 26 | AC40: 27 | AD40: 28 | AE40: 29 | AF40: 30 | AG40: 31
C41: =COUNTIF(C8:C15,"✓") | D41: =COUNTIF(D8:D15,"✓") | E41: =COUNTIF(E8:E15,"✓") | F41: =COUNTIF(F8:F15,"✓") | G41: =COUNTIF(G8:G15,"✓") | H41: =COUNTIF(H8:H15,"✓") | I41: =COUNTIF(I8:I15,"✓") | J41: =COUNTIF(J8:J15,"✓") | ... AG41: =COUNTIF(AG8:AG15,"✓")

Sheet Lists
B1: Yes | C1: Groceries/Food | D1: Tax refund (one-time) | E1: Influencer campaign | F1: Software/Subscriptions | G1: On track
A2: ✓ | B2: No | C2: Takeout/Dining | D2: CGEB top-up (one-time) | E2: Social media management | F2: Gear/Equipment | G2: Behind
C3: Transport | D3: CGEB (quarterly) | E3: Content/UGC | F3: Other | G3: Ahead
C4: Entertainment | D4: OTB (monthly) | E4: Other
C5: Personal/Shopping | D5: Other government payment
C6: Other

Sheet MonthData
A1: MonthDate | B1: Month | C1: Paycheque | D1: Gov't | E1: Side | F1: Total Income | G1: Fixed | H1: Extras | I1: Bills | J1: Total Expenses | K1: Leftover | L1: Cumulative | M1: Inc(shown) | N1: Exp(shown)
A2: 46174 | B2: =TEXT(A2,"mmm yyyy") | C2: =SUMIFS(Pay_Net,Pay_Date,">="&A2,Pay_Date,"<"&EDATE(A2,1)) | D2: =SUMPRODUCT(Gov_Amt*(Gov_Start<=A2)*(((Gov_Int=0)*(Gov_Start=A2))+((Gov_Int>0)*(MOD((YEAR(A2)-YEAR(Gov_Start))*12+MONTH(A2)-MONTH(Gov_Start),IF(Gov_Int=0,1,Gov_Int))=0)))) | E2: =SUMIFS(Side_Inc_Amt,Side_Inc_Date,">="&A2,Side_Inc_Date,"<"&EDATE(A2,1)) | F2: =C2+D2+E2 | G2: =SUMPRODUCT(Fixed_Amt*(Fixed_Start<=A2)) | H2: =SUMIFS(Disc_Amt,Disc_Date,">="&A2,Disc_Date,"<"&EDATE(A2,1)) | I2: =SUMPRODUCT(Bill_Amt*(Bill_InBudget="Yes")*(Bill_Start<=A2))+SUMIFS(Plan_Amt,Plan_Date,">="&A2,Plan_Date,"<"&EDATE(A2,1)) | J2: =G2+H2+I2 | K2: =F2-J2 | L2: =IF(C2>0,K2,0) | M2: =IF(C2>0,F2,NA()) | N2: =IF(C2>0,J2,NA())
A3: 46204 | B3: =TEXT(A3,"mmm yyyy") | C3: =SUMIFS(Pay_Net,Pay_Date,">="&A3,Pay_Date,"<"&EDATE(A3,1)) | D3: =SUMPRODUCT(Gov_Amt*(Gov_Start<=A3)*(((Gov_Int=0)*(Gov_Start=A3))+((Gov_Int>0)*(MOD((YEAR(A3)-YEAR(Gov_Start))*12+MONTH(A3)-MONTH(Gov_Start),IF(Gov_Int=0,1,Gov_Int))=0)))) | E3: =SUMIFS(Side_Inc_Amt,Side_Inc_Date,">="&A3,Side_Inc_Date,"<"&EDATE(A3,1)) | F3: =C3+D3+E3 | G3: =SUMPRODUCT(Fixed_Amt*(Fixed_Start<=A3)) | H3: =SUMIFS(Disc_Amt,Disc_Date,">="&A3,Disc_Date,"<"&EDATE(A3,1)) | I3: =SUMPRODUCT(Bill_Amt*(Bill_InBudget="Yes")*(Bill_Start<=A3))+SUMIFS(Plan_Amt,Plan_Date,">="&A3,Plan_Date,"<"&EDATE(A3,1)) | J3: =G3+H3+I3 | K3: =F3-J3 | L3: =L2+IF(C3>0,K3,0) | M3: =IF(C3>0,F3,NA()) | N3: =IF(C3>0,J3,NA())
A4: 46235 | B4: =TEXT(A4,"mmm yyyy") | C4: =SUMIFS(Pay_Net,Pay_Date,">="&A4,Pay_Date,"<"&EDATE(A4,1)) | D4: =SUMPRODUCT(Gov_Amt*(Gov_Start<=A4)*(((Gov_Int=0)*(Gov_Start=A4))+((Gov_Int>0)*(MOD((YEAR(A4)-YEAR(Gov_Start))*12+MONTH(A4)-MONTH(Gov_Start),IF(Gov_Int=0,1,Gov_Int))=0)))) | E4: =SUMIFS(Side_Inc_Amt,Side_Inc_Date,">="&A4,Side_Inc_Date,"<"&EDATE(A4,1)) | F4: =C4+D4+E4 | G4: =SUMPRODUCT(Fixed_Amt*(Fixed_Start<=A4)) | H4: =SUMIFS(Disc_Amt,Disc_Date,">="&A4,Disc_Date,"<"&EDATE(A4,1)) | I4: =SUMPRODUCT(Bill_Amt*(Bill_InBudget="Yes")*(Bill_Start<=A4))+SUMIFS(Plan_Amt,Plan_Date,">="&A4,Plan_Date,"<"&EDATE(A4,1)) | J4: =G4+H4+I4 | K4: =F4-J4 | L4: =L3+IF(C4>0,K4,0) | M4: =IF(C4>0,F4,NA()) | N4: =IF(C4>0,J4,NA())
A5: 46266 | B5: =TEXT(A5,"mmm yyyy") | C5: =SUMIFS(Pay_Net,Pay_Date,">="&A5,Pay_Date,"<"&EDATE(A5,1)) | D5: =SUMPRODUCT(Gov_Amt*(Gov_Start<=A5)*(((Gov_Int=0)*(Gov_Start=A5))+((Gov_Int>0)*(MOD((YEAR(A5)-YEAR(Gov_Start))*12+MONTH(A5)-MONTH(Gov_Start),IF(Gov_Int=0,1,Gov_Int))=0)))) | E5: =SUMIFS(Side_Inc_Amt,Side_Inc_Date,">="&A5,Side_Inc_Date,"<"&EDATE(A5,1)) | F5: =C5+D5+E5 | G5: =SUMPRODUCT(Fixed_Amt*(Fixed_Start<=A5)) | H5: =SUMIFS(Disc_Amt,Disc_Date,">="&A5,Disc_Date,"<"&EDATE(A5,1)) | I5: =SUMPRODUCT(Bill_Amt*(Bill_InBudget="Yes")*(Bill_Start<=A5))+SUMIFS(Plan_Amt,Plan_Date,">="&A5,Plan_Date,"<"&EDATE(A5,1)) | J5: =G5+H5+I5 | K5: =F5-J5 | L5: =L4+IF(C5>0,K5,0) | M5: =IF(C5>0,F5,NA()) | N5: =IF(C5>0,J5,NA())
A6: 46296 | B6: =TEXT(A6,"mmm yyyy") | C6: =SUMIFS(Pay_Net,Pay_Date,">="&A6,Pay_Date,"<"&EDATE(A6,1)) | D6: =SUMPRODUCT(Gov_Amt*(Gov_Start<=A6)*(((Gov_Int=0)*(Gov_Start=A6))+((Gov_Int>0)*(MOD((YEAR(A6)-YEAR(Gov_Start))*12+MONTH(A6)-MONTH(Gov_Start),IF(Gov_Int=0,1,Gov_Int))=0)))) | E6: =SUMIFS(Side_Inc_Amt,Side_Inc_Date,">="&A6,Side_Inc_Date,"<"&EDATE(A6,1)) | F6: =C6+D6+E6 | G6: =SUMPRODUCT(Fixed_Amt*(Fixed_Start<=A6)) | H6: =SUMIFS(Disc_Amt,Disc_Date,">="&A6,Disc_Date,"<"&EDATE(A6,1)) | I6: =SUMPRODUCT(Bill_Amt*(Bill_InBudget="Yes")*(Bill_Start<=A6))+SUMIFS(Plan_Amt,Plan_Date,">="&A6,Plan_Date,"<"&EDATE(A6,1)) | J6: =G6+H6+I6 | K6: =F6-J6 | L6: =L5+IF(C6>0,K6,0) | M6: =IF(C6>0,F6,NA()) | N6: =IF(C6>0,J6,NA())
A7: 46327 | B7: =TEXT(A7,"mmm yyyy") | C7: =SUMIFS(Pay_Net,Pay_Date,">="&A7,Pay_Date,"<"&EDATE(A7,1)) | D7: =SUMPRODUCT(Gov_Amt*(Gov_Start<=A7)*(((Gov_Int=0)*(Gov_Start=A7))+((Gov_Int>0)*(MOD((YEAR(A7)-YEAR(Gov_Start))*12+MONTH(A7)-MONTH(Gov_Start),IF(Gov_Int=0,1,Gov_Int))=0)))) | E7: =SUMIFS(Side_Inc_Amt,Side_Inc_Date,">="&A7,Side_Inc_Date,"<"&EDATE(A7,1)) | F7: =C7+D7+E7 | G7: =SUMPRODUCT(Fixed_Amt*(Fixed_Start<=A7)) | H7: =SUMIFS(Disc_Amt,Disc_Date,">="&A7,Disc_Date,"<"&EDATE(A7,1)) | I7: =SUMPRODUCT(Bill_Amt*(Bill_InBudget="Yes")*(Bill_Start<=A7))+SUMIFS(Plan_Amt,Plan_Date,">="&A7,Plan_Date,"<"&EDATE(A7,1)) | J7: =G7+H7+I7 | K7: =F7-J7 | L7: =L6+IF(C7>0,K7,0) | M7: =IF(C7>0,F7,NA()) | N7: =IF(C7>0,J7,NA())
A8: 46357 | B8: =TEXT(A8,"mmm yyyy") | C8: =SUMIFS(Pay_Net,Pay_Date,">="&A8,Pay_Date,"<"&EDATE(A8,1)) | D8: =SUMPRODUCT(Gov_Amt*(Gov_Start<=A8)*(((Gov_Int=0)*(Gov_Start=A8))+((Gov_Int>0)*(MOD((YEAR(A8)-YEAR(Gov_Start))*12+MONTH(A8)-MONTH(Gov_Start),IF(Gov_Int=0,1,Gov_Int))=0)))) | E8: =SUMIFS(Side_Inc_Amt,Side_Inc_Date,">="&A8,Side_Inc_Date,"<"&EDATE(A8,1)) | F8: =C8+D8+E8 | G8: =SUMPRODUCT(Fixed_Amt*(Fixed_Start<=A8)) | H8: =SUMIFS(Disc_Amt,Disc_Date,">="&A8,Disc_Date,"<"&EDATE(A8,1)) | I8: =SUMPRODUCT(Bill_Amt*(Bill_InBudget="Yes")*(Bill_Start<=A8))+SUMIFS(Plan_Amt,Plan_Date,">="&A8,Plan_Date,"<"&EDATE(A8,1)) | J8: =G8+H8+I8 | K8: =F8-J8 | L8: =L7+IF(C8>0,K8,0) | M8: =IF(C8>0,F8,NA()) | N8: =IF(C8>0,J8,NA())
A9: 46388 | B9: =TEXT(A9,"mmm yyyy") | C9: =SUMIFS(Pay_Net,Pay_Date,">="&A9,Pay_Date,"<"&EDATE(A9,1)) | D9: =SUMPRODUCT(Gov_Amt*(Gov_Start<=A9)*(((Gov_Int=0)*(Gov_Start=A9))+((Gov_Int>0)*(MOD((YEAR(A9)-YEAR(Gov_Start))*12+MONTH(A9)-MONTH(Gov_Start),IF(Gov_Int=0,1,Gov_Int))=0)))) | E9: =SUMIFS(Side_Inc_Amt,Side_Inc_Date,">="&A9,Side_Inc_Date,"<"&EDATE(A9,1)) | F9: =C9+D9+E9 | G9: =SUMPRODUCT(Fixed_Amt*(Fixed_Start<=A9)) | H9: =SUMIFS(Disc_Amt,Disc_Date,">="&A9,Disc_Date,"<"&EDATE(A9,1)) | I9: =SUMPRODUCT(Bill_Amt*(Bill_InBudget="Yes")*(Bill_Start<=A9))+SUMIFS(Plan_Amt,Plan_Date,">="&A9,Plan_Date,"<"&EDATE(A9,1)) | J9: =G9+H9+I9 | K9: =F9-J9 | L9: =L8+IF(C9>0,K9,0) | M9: =IF(C9>0,F9,NA()) | N9: =IF(C9>0,J9,NA())
A10: 46419 | B10: =TEXT(A10,"mmm yyyy") | C10: =SUMIFS(Pay_Net,Pay_Date,">="&A10,Pay_Date,"<"&EDATE(A10,1)) | D10: =SUMPRODUCT(Gov_Amt*(Gov_Start<=A10)*(((Gov_Int=0)*(Gov_Start=A10))+((Gov_Int>0)*(MOD((YEAR(A10)-YEAR(Gov_Start))*12+MONTH(A10)-MONTH(Gov_Start),IF(Gov_Int=0,1,Gov_Int))=0)))) | E10: =SUMIFS(Side_Inc_Amt,Side_Inc_Date,">="&A10,Side_Inc_Date,"<"&EDATE(A10,1)) | F10: =C10+D10+E10 | G10: =SUMPRODUCT(Fixed_Amt*(Fixed_Start<=A10)) | H10: =SUMIFS(Disc_Amt,Disc_Date,">="&A10,Disc_Date,"<"&EDATE(A10,1)) | I10: =SUMPRODUCT(Bill_Amt*(Bill_InBudget="Yes")*(Bill_Start<=A10))+SUMIFS(Plan_Amt,Plan_Date,">="&A10,Plan_Date,"<"&EDATE(A10,1)) | J10: =G10+H10+I10 | K10: =F10-J10 | L10: =L9+IF(C10>0,K10,0) | M10: =IF(C10>0,F10,NA()) | N10: =IF(C10>0,J10,NA())
A11: 46447 | B11: =TEXT(A11,"mmm yyyy") | C11: =SUMIFS(Pay_Net,Pay_Date,">="&A11,Pay_Date,"<"&EDATE(A11,1)) | D11: =SUMPRODUCT(Gov_Amt*(Gov_Start<=A11)*(((Gov_Int=0)*(Gov_Start=A11))+((Gov_Int>0)*(MOD((YEAR(A11)-YEAR(Gov_Start))*12+MONTH(A11)-MONTH(Gov_Start),IF(Gov_Int=0,1,Gov_Int))=0)))) | E11: =SUMIFS(Side_Inc_Amt,Side_Inc_Date,">="&A11,Side_Inc_Date,"<"&EDATE(A11,1)) | F11: =C11+D11+E11 | G11: =SUMPRODUCT(Fixed_Amt*(Fixed_Start<=A11)) | H11: =SUMIFS(Disc_Amt,Disc_Date,">="&A11,Disc_Date,"<"&EDATE(A11,1)) | I11: =SUMPRODUCT(Bill_Amt*(Bill_InBudget="Yes")*(Bill_Start<=A11))+SUMIFS(Plan_Amt,Plan_Date,">="&A11,Plan_Date,"<"&EDATE(A11,1)) | J11: =G11+H11+I11 | K11: =F11-J11 | L11: =L10+IF(C11>0,K11,0) | M11: =IF(C11>0,F11,NA()) | N11: =IF(C11>0,J11,NA())
A12: 46478 | B12: =TEXT(A12,"mmm yyyy") | C12: =SUMIFS(Pay_Net,Pay_Date,">="&A12,Pay_Date,"<"&EDATE(A12,1)) | D12: =SUMPRODUCT(Gov_Amt*(Gov_Start<=A12)*(((Gov_Int=0)*(Gov_Start=A12))+((Gov_Int>0)*(MOD((YEAR(A12)-YEAR(Gov_Start))*12+MONTH(A12)-MONTH(Gov_Start),IF(Gov_Int=0,1,Gov_Int))=0)))) | E12: =SUMIFS(Side_Inc_Amt,Side_Inc_Date,">="&A12,Side_Inc_Date,"<"&EDATE(A12,1)) | F12: =C12+D12+E12 | G12: =SUMPRODUCT(Fixed_Amt*(Fixed_Start<=A12)) | H12: =SUMIFS(Disc_Amt,Disc_Date,">="&A12,Disc_Date,"<"&EDATE(A12,1)) | I12: =SUMPRODUCT(Bill_Amt*(Bill_InBudget="Yes")*(Bill_Start<=A12))+SUMIFS(Plan_Amt,Plan_Date,">="&A12,Plan_Date,"<"&EDATE(A12,1)) | J12: =G12+H12+I12 | K12: =F12-J12 | L12: =L11+IF(C12>0,K12,0) | M12: =IF(C12>0,F12,NA()) | N12: =IF(C12>0,J12,NA())
A13: 46508 | B13: =TEXT(A13,"mmm yyyy") | C13: =SUMIFS(Pay_Net,Pay_Date,">="&A13,Pay_Date,"<"&EDATE(A13,1)) | D13: =SUMPRODUCT(Gov_Amt*(Gov_Start<=A13)*(((Gov_Int=0)*(Gov_Start=A13))+((Gov_Int>0)*(MOD((YEAR(A13)-YEAR(Gov_Start))*12+MONTH(A13)-MONTH(Gov_Start),IF(Gov_Int=0,1,Gov_Int))=0)))) | E13: =SUMIFS(Side_Inc_Amt,Side_Inc_Date,">="&A13,Side_Inc_Date,"<"&EDATE(A13,1)) | F13: =C13+D13+E13 | G13: =SUMPRODUCT(Fixed_Amt*(Fixed_Start<=A13)) | H13: =SUMIFS(Disc_Amt,Disc_Date,">="&A13,Disc_Date,"<"&EDATE(A13,1)) | I13: =SUMPRODUCT(Bill_Amt*(Bill_InBudget="Yes")*(Bill_Start<=A13))+SUMIFS(Plan_Amt,Plan_Date,">="&A13,Plan_Date,"<"&EDATE(A13,1)) | J13: =G13+H13+I13 | K13: =F13-J13 | L13: =L12+IF(C13>0,K13,0) | M13: =IF(C13>0,F13,NA()) | N13: =IF(C13>0,J13,NA())
